{
    "id": "dnd5e-spellpoints-custom",
    "title": "Advanced Magic - Spell Points System 5e Custom",
    "description": "FoundryVTT module for Spell Points System in D&amp;D5e. This module use the optional rules found on DMG to allow character to cast spells using a resource named 'Spell Points'",
    "version": "3.2.11",
    "compatibility": {
        "minimum": "13",
        "verified": "13"
    },
    "relationships": {
        "systems": [
            {
                "id": "dnd5e",
                "type": "system",
                "manifest": "https://raw.githubusercontent.com/foundryvtt/dnd5e/master/system.json",
                "compatibility": {
                    "verified": "5.0.4",
                    "minimum": "5.0.0"
                }
            }
        ]
    },
    "url": "https://github.com/SkyDroxy/dnd5e-spellpoints-custom",
    "manifest": "https://github.com/SkyDroxy/dnd5e-spellpoints-custom/releases/latest/download/module.json",
    "download": "https://github.com/SkyDroxy/dnd5e-spellpoints-custom/releases/download/v3.2.11/dnd5e-spellpoints-custom.zip",
    "authors": [
        {
            "name": "SkyDroxy",
            "url": "https://github.com/SkyDroxy",
            "flags": {}
        }
    ],
    "esmodules": [
        "scripts/main.js"
    ],
    "styles": [
        "css/sp-styles.css"
    ],
    "packs": [
        {
            "name": "module-items",
            "label": "Spell Points",
            "path": "packs/items",
            "type": "Item",
            "system": "dnd5e",
            "ownership": {
                "PLAYER": "OBSERVER",
                "ASSISTANT": "OWNER"
            },
            "flags": {}
        }
    ],
    "languages": [
        {
            "lang": "en",
            "name": "English",
            "path": "lang/en.json",
            "flags": {}
        },
        {
            "lang": "it",
            "name": "Italiano",
            "path": "lang/it.json",
            "flags": {}
        },
        {
            "lang": "es",
            "name": "Español",
            "path": "lang/es.json",
            "flags": {}
        },
        {
            "lang": "fr",
            "name": "Français",
            "path": "lang/fr.json",
            "flags": {}
        },
        {
            "lang": "de",
            "name": "Deutsch",
            "path": "lang/de.json",
            "flags": {}
        },
        {
            "lang": "pt-BR",
            "name": "Português (Brasil)",
            "path": "lang/pt-BR.json",
            "flags": {}
        }
    ],
    "media": [
        {
            "type": "icon",
            "url": "modules/dnd5e-spellpoints-custom/img/mana-icon.webp"
        },
        {
            "type": "setup",
            "url": "modules/dnd5e-spellpoints-custom/img/AdvancedMagic.webp"
        },
        {
            "type": "cover",
            "url": "modules/dnd5e-spellpoints-custom/img/AdvancedMagic.webp"
        }
    ]
}